{"type":"Topology","objects":{"districts":{"type":"GeometryCollection","geometries":[{"type":"Polygon","arcs":[[0]],"properties":{"name":"Dharwad","state":"Karnataka"}},{"type":"Polygon","arcs":[[1]],"properties":{"name":"Ludhiana","state":"Punjab"}},{"type":"Polygon","arcs":[[2]],"properties":{"name":"Nagpur","state":"Maharashtra"}}]}},"arcs":[[[110,110],[50,0],[0,50],[-50,-50]],[[210,210],[50,0],[0,50],[-50,-50]],[[160,160],[50,0],[0,50],[-50,-50]]],"transform":{"scale":[1,1],"translate":[0,0]}}